demo_file_reader/__init__.py
demo_file_reader/__main__.py
demo_file_reader/multireader.py
demo_file_reader/compressed/__init__.py
demo_file_reader/compressed/bzipped.py
demo_file_reader/compressed/gzipped.py
demo_file_reader/util/__init__.py
demo_file_reader/util/writer.py
demo_file_reader-1.0.0.dist-info/METADATA
demo_file_reader-1.0.0.dist-info/WHEEL
demo_file_reader-1.0.0.dist-info/top_level.txt
demo_file_reader-1.0.0.dist-info/RECORD
