Metadata-Version: 2.1
Name: demo-file-reader
Version: 1.0.0
Summary: Tool to read various compressed/raw file formats
Home-page: UNKNOWN
Author: UNKNOWN
Author-email: UNKNOWN
License: UNKNOWN
Platform: UNKNOWN
